{
  "animateLoading": true,
  "borderRadius": "{{appsmith.theme.borderRadius.appBorderRadius}}",
  "bottomRow": 36,
  "boxShadow": "none",
  "buttonColor": "{{appsmith.theme.colors.primaryColor}}",
  "buttonVariant": "PRIMARY",
  "disabledWhenInvalid": false,
  "dynamicBindingPathList": [
    {
      "key": "buttonColor"
    },
    {
      "key": "borderRadius"
    }
  ],
  "dynamicTriggerPathList": [
    {
      "key": "onClick"
    }
  ],
  "isDefaultClickDisabled": true,
  "isDisabled": false,
  "isLoading": false,
  "isVisible": true,
  "key": "v23rouyayb",
  "leftColumn": 23,
  "minWidth": 120,
  "mobileBottomRow": 44,
  "mobileLeftColumn": 31,
  "mobileRightColumn": 47,
  "mobileTopRow": 40,
  "needsErrorInfo": false,
  "onClick": "{{ChangePasswordJSObject.changepassword();}}",
  "parentColumnSpace": 12.9990234375,
  "parentId": "mg28133hgt",
  "parentRowSpace": 10,
  "placement": "CENTER",
  "recaptchaType": "V3",
  "renderMode": "CANVAS",
  "resetFormOnClick": false,
  "responsiveBehavior": "hug",
  "rightColumn": 39,
  "text": "Reset Password",
  "topRow": 32,
  "type": "BUTTON_WIDGET",
  "version": 1,
  "widgetId": "mmfcyij0wl",
  "widgetName": "Button1"
}