{
  "gitSyncId": "66f4e75573f83b5809d9de24_59f38cc9-209d-4cee-9c87-c2a94f1de805",
  "id": "MemberProfilePage_educationAndWorkexJsObject.workexs",
  "pluginId": "js-plugin",
  "pluginType": "JS",
  "unpublishedAction": {
    "actionConfiguration": {
      "encodeParamsToggle": true,
      "jsArguments": [],
      "paginationType": "NONE",
      "timeoutInMillisecond": 10000
    },
    "collectionId": "MemberProfilePage_educationAndWorkexJsObject",
    "confirmBeforeExecute": false,
    "datasource": {
      "isAutoGenerated": false,
      "name": "UNUSED_DATASOURCE",
      "pluginId": "js-plugin"
    },
    "dynamicBindingPathList": [
      {
        "key": "body"
      }
    ],
    "executeOnLoad": true,
    "fullyQualifiedName": "educationAndWorkexJsObject.workexs",
    "name": "workexs",
    "pageId": "MemberProfilePage",
    "userSetOnLoad": false
  }
}